pyrobex/__init__.py
pyrobex/cli.py
pyrobex/errors.py
pyrobex/io.py
pyrobex/robex.py
pyrobex/ROBEX/ROBEX
pyrobex/ROBEX/license.txt
pyrobex/ROBEX/readme.txt
pyrobex/ROBEX/runROBEX.sh
pyrobex/ROBEX/dat/256.dat
pyrobex/ROBEX/dat/EDGES_ir.dat
pyrobex/ROBEX/dat/EDGES_jc.dat
pyrobex/ROBEX/dat/EDGES_pr.dat
pyrobex/ROBEX/dat/PHI.dat
pyrobex/ROBEX/dat/PHI2.dat
pyrobex/ROBEX/dat/T_ir.dat
pyrobex/ROBEX/dat/T_jc.dat
pyrobex/ROBEX/dat/T_pr.dat
pyrobex/ROBEX/dat/bestvar.dat
pyrobex/ROBEX/dat/classwt.dat
pyrobex/ROBEX/dat/cutoff.dat
pyrobex/ROBEX/dat/face.dat
pyrobex/ROBEX/dat/lambda.dat
pyrobex/ROBEX/dat/lambda2.dat
pyrobex/ROBEX/dat/mean_normals.dat
pyrobex/ROBEX/dat/mu.dat
pyrobex/ROBEX/dat/ndbigtree.dat
pyrobex/ROBEX/dat/nodeclass.dat
pyrobex/ROBEX/dat/nodestatus.dat
pyrobex/ROBEX/dat/treemap.dat
pyrobex/ROBEX/dat/xbestsplit.dat
pyrobex/ROBEX/ref_vols/Mini.nii.gz
pyrobex/ROBEX/ref_vols/atlas.nii.gz
pyrobex/ROBEX/ref_vols/atlas_mask.nii.gz
pyrobex/ROBEX/ref_vols/atlas_mask_dilated.nii.gz
pyrobex/ROBEX/ref_vols/atlas_mask_eroded.nii.gz
pyrobex-0.4.3.dist-info/AUTHORS.rst
pyrobex-0.4.3.dist-info/LICENSE
pyrobex-0.4.3.dist-info/METADATA
pyrobex-0.4.3.dist-info/WHEEL
pyrobex-0.4.3.dist-info/entry_points.txt
pyrobex-0.4.3.dist-info/top_level.txt
pyrobex-0.4.3.dist-info/RECORD
