Metadata-Version: 2.1
Name: pyrobex
Version: 0.4.3
Summary: python bindings for ROBEX brain extraction
Home-page: https://github.com/jcreinhold/pyrobex
Author: Jacob Reinhold
Author-email: jcreinhold@gmail.com
License: BSD license
Keywords: robex,brain extraction,mri
Classifier: Development Status :: 2 - Pre-Alpha
Classifier: Intended Audience :: Developers
Classifier: License :: OSI Approved :: BSD License
Classifier: Natural Language :: English
Classifier: Programming Language :: Python :: 3
Classifier: Programming Language :: Python :: 3.7
Classifier: Programming Language :: Python :: 3.8
Classifier: Programming Language :: Python :: 3.9
Requires-Python: >=3.7
License-File: LICENSE
License-File: AUTHORS.rst
Requires-Dist: nibabel
Requires-Dist: numpy
